langvio/__init__.py
langvio/cli.py
langvio/config.py
langvio/default_config.yaml
langvio/core/__init__.py
langvio/core/base.py
langvio/core/pipeline.py
langvio/core/processor_manager.py
langvio/core/registry.py
langvio/core/visualization_manager.py
langvio/llm/__init__.py
langvio/llm/base.py
langvio/llm/factory.py
langvio/llm/google.py
langvio/llm/openai.py
langvio/media/__init__.py
langvio/media/image_visualizer.py
langvio/media/processor.py
langvio/media/video_visualizer.py
langvio/media/yolo_world_video_visualizer.py
langvio/prompts/__init__.py
langvio/prompts/constants.py
langvio/prompts/templates.py
langvio/utils/__init__.py
langvio/utils/file_utils.py
langvio/utils/llm_utils.py
langvio/utils/logging.py
langvio/utils/detection/__init__.py
langvio/utils/detection/compression.py
langvio/utils/detection/extraction.py
langvio/utils/spatial/__init__.py
langvio/utils/spatial/relationships.py
langvio/utils/tracking/__init__.py
langvio/utils/tracking/bytetracker_manager.py
langvio/utils/tracking/tracker_file_manager.py
langvio/vision/__init__.py
langvio/vision/base.py
langvio/vision/color_detection.py
langvio/vision/utils.py
langvio/vision/yolo_world/__init__.py
langvio/vision/yolo_world/detector.py
langvio/vision/yolo_world/image_processor.py
langvio/vision/yolo_world/video_processor.py
langvio-0.0.5.dist-info/licenses/LICENSE
langvio-0.0.5.dist-info/METADATA
langvio-0.0.5.dist-info/WHEEL
langvio-0.0.5.dist-info/entry_points.txt
langvio-0.0.5.dist-info/top_level.txt
langvio-0.0.5.dist-info/RECORD
