Metadata-Version: 2.4
Name: langvio
Version: 0.0.5
Summary: Connect language models to vision models for natural language visual analysis
Author: Mughees Mehdi
Author-email: Mughees Mehdi <mugheesmehdi@gmail.com>
License: MIT
Project-URL: Homepage, https://github.com/MugheesMehdi07/langvio
Project-URL: Documentation, https://github.com/MugheesMehdi07/langvio#readme
Project-URL: Repository, https://github.com/MugheesMehdi07/langvio
Project-URL: Issues, https://github.com/MugheesMehdi07/langvio/issues
Project-URL: Changelog, https://github.com/MugheesMehdi07/langvio/blob/main/CHANGELOG.md
Keywords: computer-vision,llm,ai,yolo,langchain,object-detection
Classifier: Development Status :: 3 - Alpha
Classifier: Intended Audience :: Developers
Classifier: License :: OSI Approved :: MIT License
Classifier: Programming Language :: Python :: 3
Classifier: Programming Language :: Python :: 3.8
Classifier: Programming Language :: Python :: 3.9
Classifier: Programming Language :: Python :: 3.10
Classifier: Programming Language :: Python :: 3.11
Classifier: Programming Language :: Python :: 3.12
Classifier: Topic :: Scientific/Engineering :: Artificial Intelligence
Classifier: Topic :: Software Development :: Libraries :: Python Modules
Classifier: Topic :: Multimedia :: Graphics :: 3D Modeling
Classifier: Topic :: Text Processing :: Linguistic
Requires-Python: >=3.8,<3.13
License-File: LICENSE
Requires-Dist: torch>=2.9.1
Requires-Dist: ultralytics>=8.3.240
Requires-Dist: opencv-python>=4.12.0.88
Requires-Dist: numpy>=2.2.6
Requires-Dist: pillow>=12.0.0
Requires-Dist: langchain-core>=1.2.2
Requires-Dist: langchain-community>=0.4.1
Requires-Dist: pyyaml>=6.0.3
Requires-Dist: python-dotenv>=1.2.1
Requires-Dist: tqdm>=4.67.1
Provides-Extra: openai
Requires-Dist: openai>=1.0.0; extra == "openai"
Requires-Dist: langchain-openai>=0.0.1; extra == "openai"
Provides-Extra: google
Requires-Dist: google-generativeai<1.0.0,>=0.3.0; extra == "google"
Requires-Dist: langchain-google-genai>=2.0.0; extra == "google"
Provides-Extra: all-llm
Requires-Dist: langvio[google,openai]; extra == "all-llm"
Provides-Extra: webapp
Requires-Dist: flask>=2.0.0; extra == "webapp"
Requires-Dist: werkzeug>=2.0.0; extra == "webapp"
Provides-Extra: dev
Requires-Dist: pytest>=7.0.0; extra == "dev"
Requires-Dist: pytest-cov>=4.0.0; extra == "dev"
Requires-Dist: black>=22.0.0; extra == "dev"
Requires-Dist: isort>=5.10.0; extra == "dev"
Requires-Dist: flake8>=5.0.0; extra == "dev"
Requires-Dist: mypy>=1.0.0; extra == "dev"
Dynamic: author
Dynamic: license-file
Dynamic: requires-python
